<?xml version="1.0" encoding="UTF-8"?>

<!-- generated on 2025-10-16 20:29:36 by Eclipse SUMO GUI Version 1.22.0
<sumoConfiguration xmlns:xsi="http://www.w3.org/2001/XMLSchema-instance" xsi:noNamespaceSchemaLocation="http://sumo.dlr.de/xsd/sumoConfiguration.xsd">

    <input>
        <net-file value="osm.net.xml.gz"/>
        <route-files value="osm.passenger.trips.xml"/>
        <additional-files value="osm.poly.xml.gz"/>
    </input>

    <time>
        <step-length value="0.05"/>
    </time>

    <processing>
        <lateral-resolution value="0.1"/>
        <ignore-route-errors value="true"/>
        <tls.actuated.jam-threshold value="30"/>
    </processing>

    <routing>
        <device.rerouting.adaptation-steps value="18"/>
        <device.rerouting.adaptation-interval value="10"/>
    </routing>

    <report>
        <verbose value="true"/>
        <duration-log.statistics value="true"/>
        <no-step-log value="true"/>
    </report>

    <traci_server>
        <remote-port value="57049"/>
    </traci_server>

    <gui_only>
        <gui-settings-file value="osm.view.xml"/>
        <delay value="1000"/>
    </gui_only>

</sumoConfiguration>
-->

<detector xmlns:xsi="http://www.w3.org/2001/XMLSchema-instance" xsi:noNamespaceSchemaLocation="http://sumo.dlr.de/xsd/det_e2_file.xsd">
   <interval begin="0.00" end="3.85" id="e2_25" sampledSeconds="0.00" nVehEntered="0" nVehLeft="0" nVehSeen="0" meanSpeed="-1.00" meanTimeLoss="-1.00" meanOccupancy="0.00" maxOccupancy="0.00" meanMaxJamLengthInVehicles="0.00" meanMaxJamLengthInMeters="0.00" maxJamLengthInVehicles="0" maxJamLengthInMeters="0.00" jamLengthInVehiclesSum="0" jamLengthInMetersSum="0.00" meanHaltingDuration="0.00" maxHaltingDuration="0.00" haltingDurationSum="0.00" meanIntervalHaltingDuration="0.00" maxIntervalHaltingDuration="0.00" intervalHaltingDurationSum="0.00" startedHalts="0.00" meanVehicleNumber="0.00" maxVehicleNumber="0" />
   <interval begin="3.85" end="6.85" id="e2_25" sampledSeconds="0.00" nVehEntered="0" nVehLeft="0" nVehSeen="0" meanSpeed="-1.00" meanTimeLoss="-1.00" meanOccupancy="0.00" maxOccupancy="0.00" meanMaxJamLengthInVehicles="0.00" meanMaxJamLengthInMeters="0.00" maxJamLengthInVehicles="0" maxJamLengthInMeters="0.00" jamLengthInVehiclesSum="0" jamLengthInMetersSum="0.00" meanHaltingDuration="0.00" maxHaltingDuration="0.00" haltingDurationSum="0.00" meanIntervalHaltingDuration="0.00" maxIntervalHaltingDuration="0.00" intervalHaltingDurationSum="0.00" startedHalts="0.00" meanVehicleNumber="0.00" maxVehicleNumber="0" />
   <interval begin="6.85" end="10.70" id="e2_25" sampledSeconds="0.00" nVehEntered="0" nVehLeft="0" nVehSeen="0" meanSpeed="-1.00" meanTimeLoss="-1.00" meanOccupancy="0.00" maxOccupancy="0.00" meanMaxJamLengthInVehicles="0.00" meanMaxJamLengthInMeters="0.00" maxJamLengthInVehicles="0" maxJamLengthInMeters="0.00" jamLengthInVehiclesSum="0" jamLengthInMetersSum="0.00" meanHaltingDuration="0.00" maxHaltingDuration="0.00" haltingDurationSum="0.00" meanIntervalHaltingDuration="0.00" maxIntervalHaltingDuration="0.00" intervalHaltingDurationSum="0.00" startedHalts="0.00" meanVehicleNumber="0.00" maxVehicleNumber="0" />
   <interval begin="10.70" end="13.70" id="e2_25" sampledSeconds="0.00" nVehEntered="0" nVehLeft="0" nVehSeen="0" meanSpeed="-1.00" meanTimeLoss="-1.00" meanOccupancy="0.00" maxOccupancy="0.00" meanMaxJamLengthInVehicles="0.00" meanMaxJamLengthInMeters="0.00" maxJamLengthInVehicles="0" maxJamLengthInMeters="0.00" jamLengthInVehiclesSum="0" jamLengthInMetersSum="0.00" meanHaltingDuration="0.00" maxHaltingDuration="0.00" haltingDurationSum="0.00" meanIntervalHaltingDuration="0.00" maxIntervalHaltingDuration="0.00" intervalHaltingDurationSum="0.00" startedHalts="0.00" meanVehicleNumber="0.00" maxVehicleNumber="0" />
   <interval begin="13.70" end="18.95" id="e2_25" sampledSeconds="0.00" nVehEntered="0" nVehLeft="0" nVehSeen="0" meanSpeed="-1.00" meanTimeLoss="-1.00" meanOccupancy="0.00" maxOccupancy="0.00" meanMaxJamLengthInVehicles="0.00" meanMaxJamLengthInMeters="0.00" maxJamLengthInVehicles="0" maxJamLengthInMeters="0.00" jamLengthInVehiclesSum="0" jamLengthInMetersSum="0.00" meanHaltingDuration="0.00" maxHaltingDuration="0.00" haltingDurationSum="0.00" meanIntervalHaltingDuration="0.00" maxIntervalHaltingDuration="0.00" intervalHaltingDurationSum="0.00" startedHalts="0.00" meanVehicleNumber="0.00" maxVehicleNumber="0" />
   <interval begin="18.95" end="21.95" id="e2_25" sampledSeconds="0.00" nVehEntered="0" nVehLeft="0" nVehSeen="0" meanSpeed="-1.00" meanTimeLoss="-1.00" meanOccupancy="0.00" maxOccupancy="0.00" meanMaxJamLengthInVehicles="0.00" meanMaxJamLengthInMeters="0.00" maxJamLengthInVehicles="0" maxJamLengthInMeters="0.00" jamLengthInVehiclesSum="0" jamLengthInMetersSum="0.00" meanHaltingDuration="0.00" maxHaltingDuration="0.00" haltingDurationSum="0.00" meanIntervalHaltingDuration="0.00" maxIntervalHaltingDuration="0.00" intervalHaltingDurationSum="0.00" startedHalts="0.00" meanVehicleNumber="0.00" maxVehicleNumber="0" />
   <interval begin="21.95" end="25.80" id="e2_25" sampledSeconds="0.67" nVehEntered="1" nVehLeft="0" nVehSeen="1" meanSpeed="16.70" meanTimeLoss="0.18" meanOccupancy="2.04" maxOccupancy="14.29" meanMaxJamLengthInVehicles="0.00" meanMaxJamLengthInMeters="0.00" maxJamLengthInVehicles="0" maxJamLengthInMeters="0.00" jamLengthInVehiclesSum="0" jamLengthInMetersSum="0.00" meanHaltingDuration="0.00" maxHaltingDuration="0.00" haltingDurationSum="0.00" meanIntervalHaltingDuration="0.00" maxIntervalHaltingDuration="0.00" intervalHaltingDurationSum="0.00" startedHalts="0.00" meanVehicleNumber="0.18" maxVehicleNumber="1" />
   <interval begin="25.80" end="28.80" id="e2_25" sampledSeconds="3.00" nVehEntered="0" nVehLeft="0" nVehSeen="1" meanSpeed="8.47" meanTimeLoss="1.89" meanOccupancy="13.82" maxOccupancy="14.29" meanMaxJamLengthInVehicles="0.00" meanMaxJamLengthInMeters="0.00" maxJamLengthInVehicles="0" maxJamLengthInMeters="0.00" jamLengthInVehiclesSum="0" jamLengthInMetersSum="0.00" meanHaltingDuration="0.00" maxHaltingDuration="0.00" haltingDurationSum="0.00" meanIntervalHaltingDuration="0.00" maxIntervalHaltingDuration="0.00" intervalHaltingDurationSum="0.00" startedHalts="0.00" meanVehicleNumber="1.00" maxVehicleNumber="1" />
   <interval begin="28.80" end="34.75" id="e2_25" sampledSeconds="1.14" nVehEntered="0" nVehLeft="1" nVehSeen="1" meanSpeed="3.06" meanTimeLoss="1.00" meanOccupancy="1.03" maxOccupancy="9.67" meanMaxJamLengthInVehicles="0.00" meanMaxJamLengthInMeters="0.00" maxJamLengthInVehicles="0" maxJamLengthInMeters="0.00" jamLengthInVehiclesSum="0" jamLengthInMetersSum="0.00" meanHaltingDuration="0.00" maxHaltingDuration="0.00" haltingDurationSum="0.00" meanIntervalHaltingDuration="0.00" maxIntervalHaltingDuration="0.00" intervalHaltingDurationSum="0.00" startedHalts="0.00" meanVehicleNumber="0.19" maxVehicleNumber="1" />
   <interval begin="34.75" end="37.75" id="e2_25" sampledSeconds="0.00" nVehEntered="0" nVehLeft="0" nVehSeen="0" meanSpeed="-1.00" meanTimeLoss="-1.00" meanOccupancy="0.00" maxOccupancy="0.00" meanMaxJamLengthInVehicles="0.00" meanMaxJamLengthInMeters="0.00" maxJamLengthInVehicles="0" maxJamLengthInMeters="0.00" jamLengthInVehiclesSum="0" jamLengthInMetersSum="0.00" meanHaltingDuration="0.00" maxHaltingDuration="0.00" haltingDurationSum="0.00" meanIntervalHaltingDuration="0.00" maxIntervalHaltingDuration="0.00" intervalHaltingDurationSum="0.00" startedHalts="0.00" meanVehicleNumber="0.00" maxVehicleNumber="0" />
   <interval begin="37.75" end="52.80" id="e2_25" sampledSeconds="13.62" nVehEntered="1" nVehLeft="0" nVehSeen="1" meanSpeed="2.71" meanTimeLoss="12.21" meanOccupancy="9.24" maxOccupancy="14.29" meanMaxJamLengthInVehicles="0.59" meanMaxJamLengthInMeters="1.86" maxJamLengthInVehicles="1" maxJamLengthInMeters="3.15" jamLengthInVehiclesSum="178" jamLengthInMetersSum="560.88" meanHaltingDuration="9.90" maxHaltingDuration="9.90" haltingDurationSum="9.90" meanIntervalHaltingDuration="9.90" maxIntervalHaltingDuration="9.90" intervalHaltingDurationSum="9.90" startedHalts="1.00" meanVehicleNumber="0.91" maxVehicleNumber="1" />
   <interval begin="52.80" end="55.80" id="e2_25" sampledSeconds="3.00" nVehEntered="0" nVehLeft="0" nVehSeen="1" meanSpeed="0.00" meanTimeLoss="3.00" meanOccupancy="9.00" maxOccupancy="9.00" meanMaxJamLengthInVehicles="1.00" meanMaxJamLengthInMeters="3.15" maxJamLengthInVehicles="1" maxJamLengthInMeters="3.15" jamLengthInVehiclesSum="60" jamLengthInMetersSum="189.06" meanHaltingDuration="12.90" maxHaltingDuration="12.90" haltingDurationSum="12.90" meanIntervalHaltingDuration="3.00" maxIntervalHaltingDuration="3.00" intervalHaltingDurationSum="3.00" startedHalts="0.00" meanVehicleNumber="1.00" maxVehicleNumber="1" />
   <interval begin="55.80" end="59.65" id="e2_25" sampledSeconds="3.85" nVehEntered="0" nVehLeft="0" nVehSeen="1" meanSpeed="0.00" meanTimeLoss="3.85" meanOccupancy="9.00" maxOccupancy="9.00" meanMaxJamLengthInVehicles="1.00" meanMaxJamLengthInMeters="3.15" maxJamLengthInVehicles="1" maxJamLengthInMeters="3.15" jamLengthInVehiclesSum="77" jamLengthInMetersSum="242.63" meanHaltingDuration="16.75" maxHaltingDuration="16.75" haltingDurationSum="16.75" meanIntervalHaltingDuration="3.85" maxIntervalHaltingDuration="3.85" intervalHaltingDurationSum="3.85" startedHalts="0.00" meanVehicleNumber="1.00" maxVehicleNumber="1" />
   <interval begin="59.65" end="62.65" id="e2_25" sampledSeconds="3.00" nVehEntered="0" nVehLeft="0" nVehSeen="1" meanSpeed="0.00" meanTimeLoss="3.00" meanOccupancy="9.00" maxOccupancy="9.00" meanMaxJamLengthInVehicles="1.00" meanMaxJamLengthInMeters="3.15" maxJamLengthInVehicles="1" maxJamLengthInMeters="3.15" jamLengthInVehiclesSum="60" jamLengthInMetersSum="189.06" meanHaltingDuration="19.75" maxHaltingDuration="19.75" haltingDurationSum="19.75" meanIntervalHaltingDuration="3.00" maxIntervalHaltingDuration="3.00" intervalHaltingDurationSum="3.00" startedHalts="0.00" meanVehicleNumber="1.00" maxVehicleNumber="1" />
   <interval begin="62.65" end="68.60" id="e2_25" sampledSeconds="1.64" nVehEntered="0" nVehLeft="1" nVehSeen="1" meanSpeed="1.92" meanTimeLoss="1.33" meanOccupancy="1.59" maxOccupancy="8.98" meanMaxJamLengthInVehicles="0.09" meanMaxJamLengthInMeters="0.28" maxJamLengthInVehicles="1" maxJamLengthInMeters="3.14" jamLengthInVehiclesSum="11" jamLengthInMetersSum="32.91" meanHaltingDuration="20.30" maxHaltingDuration="20.30" haltingDurationSum="20.30" meanIntervalHaltingDuration="0.55" maxIntervalHaltingDuration="0.55" intervalHaltingDurationSum="0.55" startedHalts="0.00" meanVehicleNumber="0.28" maxVehicleNumber="1" />
   <interval begin="68.60" end="71.60" id="e2_25" sampledSeconds="0.00" nVehEntered="0" nVehLeft="0" nVehSeen="0" meanSpeed="-1.00" meanTimeLoss="-1.00" meanOccupancy="0.00" maxOccupancy="0.00" meanMaxJamLengthInVehicles="0.00" meanMaxJamLengthInMeters="0.00" maxJamLengthInVehicles="0" maxJamLengthInMeters="0.00" jamLengthInVehiclesSum="0" jamLengthInMetersSum="0.00" meanHaltingDuration="0.00" maxHaltingDuration="0.00" haltingDurationSum="0.00" meanIntervalHaltingDuration="0.00" maxIntervalHaltingDuration="0.00" intervalHaltingDurationSum="0.00" startedHalts="0.00" meanVehicleNumber="0.00" maxVehicleNumber="0" />
   <interval begin="71.60" end="86.65" id="e2_25" sampledSeconds="10.55" nVehEntered="1" nVehLeft="0" nVehSeen="1" meanSpeed="3.49" meanTimeLoss="8.89" meanOccupancy="7.40" maxOccupancy="14.29" meanMaxJamLengthInVehicles="0.39" meanMaxJamLengthInMeters="1.21" maxJamLengthInVehicles="1" maxJamLengthInMeters="3.15" jamLengthInVehiclesSum="116" jamLengthInMetersSum="365.52" meanHaltingDuration="6.80" maxHaltingDuration="6.80" haltingDurationSum="6.80" meanIntervalHaltingDuration="6.80" maxIntervalHaltingDuration="6.80" intervalHaltingDurationSum="6.80" startedHalts="1.00" meanVehicleNumber="0.70" maxVehicleNumber="1" />
   <interval begin="86.65" end="89.65" id="e2_25" sampledSeconds="3.00" nVehEntered="0" nVehLeft="0" nVehSeen="1" meanSpeed="0.00" meanTimeLoss="3.00" meanOccupancy="9.00" maxOccupancy="9.00" meanMaxJamLengthInVehicles="1.00" meanMaxJamLengthInMeters="3.15" maxJamLengthInVehicles="1" maxJamLengthInMeters="3.15" jamLengthInVehiclesSum="60" jamLengthInMetersSum="189.06" meanHaltingDuration="9.80" maxHaltingDuration="9.80" haltingDurationSum="9.80" meanIntervalHaltingDuration="3.00" maxIntervalHaltingDuration="3.00" intervalHaltingDurationSum="3.00" startedHalts="0.00" meanVehicleNumber="1.00" maxVehicleNumber="1" />
   <interval begin="89.65" end="93.50" id="e2_25" sampledSeconds="3.85" nVehEntered="0" nVehLeft="0" nVehSeen="1" meanSpeed="0.00" meanTimeLoss="3.85" meanOccupancy="9.00" maxOccupancy="9.00" meanMaxJamLengthInVehicles="1.00" meanMaxJamLengthInMeters="3.15" maxJamLengthInVehicles="1" maxJamLengthInMeters="3.15" jamLengthInVehiclesSum="77" jamLengthInMetersSum="242.63" meanHaltingDuration="13.65" maxHaltingDuration="13.65" haltingDurationSum="13.65" meanIntervalHaltingDuration="3.85" maxIntervalHaltingDuration="3.85" intervalHaltingDurationSum="3.85" startedHalts="0.00" meanVehicleNumber="1.00" maxVehicleNumber="1" />
   <interval begin="93.50" end="96.50" id="e2_25" sampledSeconds="5.56" nVehEntered="1" nVehLeft="0" nVehSeen="2" meanSpeed="3.93" meanTimeLoss="2.27" meanOccupancy="20.31" maxOccupancy="23.29" meanMaxJamLengthInVehicles="1.00" meanMaxJamLengthInMeters="3.15" maxJamLengthInVehicles="1" maxJamLengthInMeters="3.15" jamLengthInVehiclesSum="60" jamLengthInMetersSum="189.06" meanHaltingDuration="16.65" maxHaltingDuration="16.65" haltingDurationSum="16.65" meanIntervalHaltingDuration="3.00" maxIntervalHaltingDuration="3.00" intervalHaltingDurationSum="3.00" startedHalts="0.00" meanVehicleNumber="1.87" maxVehicleNumber="2" />
   <interval begin="96.50" end="104.55" id="e2_25" sampledSeconds="5.45" nVehEntered="0" nVehLeft="2" nVehSeen="2" meanSpeed="3.91" meanTimeLoss="2.13" meanOccupancy="7.23" maxOccupancy="23.27" meanMaxJamLengthInVehicles="0.07" meanMaxJamLengthInMeters="0.20" maxJamLengthInVehicles="1" maxJamLengthInMeters="3.14" jamLengthInVehiclesSum="11" jamLengthInMetersSum="32.89" meanHaltingDuration="17.20" maxHaltingDuration="17.20" haltingDurationSum="17.20" meanIntervalHaltingDuration="0.55" maxIntervalHaltingDuration="0.55" intervalHaltingDurationSum="0.55" startedHalts="0.00" meanVehicleNumber="0.68" maxVehicleNumber="2" />
   <interval begin="104.55" end="107.55" id="e2_25" sampledSeconds="0.00" nVehEntered="0" nVehLeft="0" nVehSeen="0" meanSpeed="-1.00" meanTimeLoss="-1.00" meanOccupancy="0.00" maxOccupancy="0.00" meanMaxJamLengthInVehicles="0.00" meanMaxJamLengthInMeters="0.00" maxJamLengthInVehicles="0" maxJamLengthInMeters="0.00" jamLengthInVehiclesSum="0" jamLengthInMetersSum="0.00" meanHaltingDuration="0.00" maxHaltingDuration="0.00" haltingDurationSum="0.00" meanIntervalHaltingDuration="0.00" maxIntervalHaltingDuration="0.00" intervalHaltingDurationSum="0.00" startedHalts="0.00" meanVehicleNumber="0.00" maxVehicleNumber="0" />
   <interval begin="107.55" end="119.80" id="e2_25" sampledSeconds="4.95" nVehEntered="1" nVehLeft="0" nVehSeen="1" meanSpeed="7.45" meanTimeLoss="3.38" meanOccupancy="4.97" maxOccupancy="14.29" meanMaxJamLengthInVehicles="0.02" meanMaxJamLengthInMeters="0.05" maxJamLengthInVehicles="1" maxJamLengthInMeters="3.15" jamLengthInVehiclesSum="4" jamLengthInMetersSum="12.60" meanHaltingDuration="1.20" maxHaltingDuration="1.20" haltingDurationSum="1.20" meanIntervalHaltingDuration="1.20" maxIntervalHaltingDuration="1.20" intervalHaltingDurationSum="1.20" startedHalts="1.00" meanVehicleNumber="0.40" maxVehicleNumber="1" />
   <interval begin="119.80" end="122.80" id="e2_25" sampledSeconds="3.00" nVehEntered="0" nVehLeft="0" nVehSeen="1" meanSpeed="0.00" meanTimeLoss="3.00" meanOccupancy="9.00" maxOccupancy="9.00" meanMaxJamLengthInVehicles="1.00" meanMaxJamLengthInMeters="3.15" maxJamLengthInVehicles="1" maxJamLengthInMeters="3.15" jamLengthInVehiclesSum="60" jamLengthInMetersSum="189.06" meanHaltingDuration="4.20" maxHaltingDuration="4.20" haltingDurationSum="4.20" meanIntervalHaltingDuration="3.00" maxIntervalHaltingDuration="3.00" intervalHaltingDurationSum="3.00" startedHalts="0.00" meanVehicleNumber="1.00" maxVehicleNumber="1" />
   <interval begin="122.80" end="130.85" id="e2_25" sampledSeconds="8.05" nVehEntered="0" nVehLeft="0" nVehSeen="1" meanSpeed="0.00" meanTimeLoss="8.05" meanOccupancy="9.00" maxOccupancy="9.00" meanMaxJamLengthInVehicles="1.00" meanMaxJamLengthInMeters="3.15" maxJamLengthInVehicles="1" maxJamLengthInMeters="3.15" jamLengthInVehiclesSum="161" jamLengthInMetersSum="507.31" meanHaltingDuration="12.25" maxHaltingDuration="12.25" haltingDurationSum="12.25" meanIntervalHaltingDuration="8.05" maxIntervalHaltingDuration="8.05" intervalHaltingDurationSum="8.05" startedHalts="0.00" meanVehicleNumber="1.00" maxVehicleNumber="1" />
   <interval begin="130.85" end="133.85" id="e2_25" sampledSeconds="3.00" nVehEntered="0" nVehLeft="0" nVehSeen="1" meanSpeed="0.00" meanTimeLoss="3.00" meanOccupancy="9.00" maxOccupancy="9.00" meanMaxJamLengthInVehicles="1.00" meanMaxJamLengthInMeters="3.15" maxJamLengthInVehicles="1" maxJamLengthInMeters="3.15" jamLengthInVehiclesSum="60" jamLengthInMetersSum="189.06" meanHaltingDuration="15.25" maxHaltingDuration="15.25" haltingDurationSum="15.25" meanIntervalHaltingDuration="3.00" maxIntervalHaltingDuration="3.00" intervalHaltingDurationSum="3.00" startedHalts="0.00" meanVehicleNumber="1.00" maxVehicleNumber="1" />
   <interval begin="133.85" end="139.80" id="e2_25" sampledSeconds="1.63" nVehEntered="0" nVehLeft="1" nVehSeen="1" meanSpeed="1.93" meanTimeLoss="1.51" meanOccupancy="1.58" maxOccupancy="8.98" meanMaxJamLengthInVehicles="0.09" meanMaxJamLengthInMeters="0.28" maxJamLengthInVehicles="1" maxJamLengthInMeters="3.14" jamLengthInVehiclesSum="11" jamLengthInMetersSum="32.90" meanHaltingDuration="15.80" maxHaltingDuration="15.80" haltingDurationSum="15.80" meanIntervalHaltingDuration="0.55" maxIntervalHaltingDuration="0.55" intervalHaltingDurationSum="0.55" startedHalts="0.00" meanVehicleNumber="0.28" maxVehicleNumber="1" />
   <interval begin="139.80" end="142.80" id="e2_25" sampledSeconds="0.00" nVehEntered="0" nVehLeft="0" nVehSeen="0" meanSpeed="-1.00" meanTimeLoss="-1.00" meanOccupancy="0.00" maxOccupancy="0.00" meanMaxJamLengthInVehicles="0.00" meanMaxJamLengthInMeters="0.00" maxJamLengthInVehicles="0" maxJamLengthInMeters="0.00" jamLengthInVehiclesSum="0" jamLengthInMetersSum="0.00" meanHaltingDuration="0.00" maxHaltingDuration="0.00" haltingDurationSum="0.00" meanIntervalHaltingDuration="0.00" maxIntervalHaltingDuration="0.00" intervalHaltingDurationSum="0.00" startedHalts="0.00" meanVehicleNumber="0.00" maxVehicleNumber="0" />
   <interval begin="142.80" end="160.65" id="e2_25" sampledSeconds="0.00" nVehEntered="0" nVehLeft="0" nVehSeen="0" meanSpeed="-1.00" meanTimeLoss="-1.00" meanOccupancy="0.00" maxOccupancy="0.00" meanMaxJamLengthInVehicles="0.00" meanMaxJamLengthInMeters="0.00" maxJamLengthInVehicles="0" maxJamLengthInMeters="0.00" jamLengthInVehiclesSum="0" jamLengthInMetersSum="0.00" meanHaltingDuration="0.00" maxHaltingDuration="0.00" haltingDurationSum="0.00" meanIntervalHaltingDuration="0.00" maxIntervalHaltingDuration="0.00" intervalHaltingDurationSum="0.00" startedHalts="0.00" meanVehicleNumber="0.00" maxVehicleNumber="0" />
   <interval begin="160.65" end="163.65" id="e2_25" sampledSeconds="0.00" nVehEntered="0" nVehLeft="0" nVehSeen="0" meanSpeed="-1.00" meanTimeLoss="-1.00" meanOccupancy="0.00" maxOccupancy="0.00" meanMaxJamLengthInVehicles="0.00" meanMaxJamLengthInMeters="0.00" maxJamLengthInVehicles="0" maxJamLengthInMeters="0.00" jamLengthInVehiclesSum="0" jamLengthInMetersSum="0.00" meanHaltingDuration="0.00" maxHaltingDuration="0.00" haltingDurationSum="0.00" meanIntervalHaltingDuration="0.00" maxIntervalHaltingDuration="0.00" intervalHaltingDurationSum="0.00" startedHalts="0.00" meanVehicleNumber="0.00" maxVehicleNumber="0" />
   <interval begin="163.65" end="167.50" id="e2_25" sampledSeconds="2.98" nVehEntered="1" nVehLeft="0" nVehSeen="1" meanSpeed="11.50" meanTimeLoss="1.44" meanOccupancy="10.65" maxOccupancy="14.29" meanMaxJamLengthInVehicles="0.00" meanMaxJamLengthInMeters="0.00" maxJamLengthInVehicles="0" maxJamLengthInMeters="0.00" jamLengthInVehiclesSum="0" jamLengthInMetersSum="0.00" meanHaltingDuration="0.00" maxHaltingDuration="0.00" haltingDurationSum="0.00" meanIntervalHaltingDuration="0.00" maxIntervalHaltingDuration="0.00" intervalHaltingDurationSum="0.00" startedHalts="0.00" meanVehicleNumber="0.78" maxVehicleNumber="1" />
   <interval begin="167.50" end="170.50" id="e2_25" sampledSeconds="3.00" nVehEntered="0" nVehLeft="0" nVehSeen="1" meanSpeed="0.85" meanTimeLoss="2.89" meanOccupancy="9.77" maxOccupancy="14.29" meanMaxJamLengthInVehicles="0.42" meanMaxJamLengthInMeters="1.31" maxJamLengthInVehicles="1" maxJamLengthInMeters="3.15" jamLengthInVehiclesSum="25" jamLengthInMetersSum="78.78" meanHaltingDuration="2.25" maxHaltingDuration="2.25" haltingDurationSum="2.25" meanIntervalHaltingDuration="2.25" maxIntervalHaltingDuration="2.25" intervalHaltingDurationSum="2.25" startedHalts="1.00" meanVehicleNumber="1.00" maxVehicleNumber="1" />
   <interval begin="170.50" end="178.55" id="e2_25" sampledSeconds="1.62" nVehEntered="0" nVehLeft="1" nVehSeen="1" meanSpeed="1.95" meanTimeLoss="1.26" meanOccupancy="1.15" maxOccupancy="8.98" meanMaxJamLengthInVehicles="0.07" meanMaxJamLengthInMeters="0.20" maxJamLengthInVehicles="1" maxJamLengthInMeters="3.14" jamLengthInVehiclesSum="11" jamLengthInMetersSum="32.87" meanHaltingDuration="2.80" maxHaltingDuration="2.80" haltingDurationSum="2.80" meanIntervalHaltingDuration="0.55" maxIntervalHaltingDuration="0.55" intervalHaltingDurationSum="0.55" startedHalts="0.00" meanVehicleNumber="0.20" maxVehicleNumber="1" />
   <interval begin="178.55" end="181.55" id="e2_25" sampledSeconds="0.00" nVehEntered="0" nVehLeft="0" nVehSeen="0" meanSpeed="-1.00" meanTimeLoss="-1.00" meanOccupancy="0.00" maxOccupancy="0.00" meanMaxJamLengthInVehicles="0.00" meanMaxJamLengthInMeters="0.00" maxJamLengthInVehicles="0" maxJamLengthInMeters="0.00" jamLengthInVehiclesSum="0" jamLengthInMetersSum="0.00" meanHaltingDuration="0.00" maxHaltingDuration="0.00" haltingDurationSum="0.00" meanIntervalHaltingDuration="0.00" maxIntervalHaltingDuration="0.00" intervalHaltingDurationSum="0.00" startedHalts="0.00" meanVehicleNumber="0.00" maxVehicleNumber="0" />
   <interval begin="181.55" end="195.20" id="e2_25" sampledSeconds="9.96" nVehEntered="1" nVehLeft="0" nVehSeen="1" meanSpeed="3.70" meanTimeLoss="8.11" meanOccupancy="7.77" maxOccupancy="14.29" meanMaxJamLengthInVehicles="0.38" meanMaxJamLengthInMeters="1.20" maxJamLengthInVehicles="1" maxJamLengthInMeters="3.15" jamLengthInVehiclesSum="104" jamLengthInMetersSum="327.70" meanHaltingDuration="6.20" maxHaltingDuration="6.20" haltingDurationSum="6.20" meanIntervalHaltingDuration="6.20" maxIntervalHaltingDuration="6.20" intervalHaltingDurationSum="6.20" startedHalts="1.00" meanVehicleNumber="0.73" maxVehicleNumber="1" />
   <interval begin="195.20" end="198.20" id="e2_25" sampledSeconds="3.00" nVehEntered="0" nVehLeft="0" nVehSeen="1" meanSpeed="0.00" meanTimeLoss="3.00" meanOccupancy="9.00" maxOccupancy="9.00" meanMaxJamLengthInVehicles="1.00" meanMaxJamLengthInMeters="3.15" maxJamLengthInVehicles="1" maxJamLengthInMeters="3.15" jamLengthInVehiclesSum="60" jamLengthInMetersSum="189.06" meanHaltingDuration="9.20" maxHaltingDuration="9.20" haltingDurationSum="9.20" meanIntervalHaltingDuration="3.00" maxIntervalHaltingDuration="3.00" intervalHaltingDurationSum="3.00" startedHalts="0.00" meanVehicleNumber="1.00" maxVehicleNumber="1" />
   <interval begin="198.20" end="208.35" id="e2_25" sampledSeconds="10.15" nVehEntered="0" nVehLeft="0" nVehSeen="1" meanSpeed="0.00" meanTimeLoss="10.15" meanOccupancy="9.00" maxOccupancy="9.00" meanMaxJamLengthInVehicles="1.00" meanMaxJamLengthInMeters="3.15" maxJamLengthInVehicles="1" maxJamLengthInMeters="3.15" jamLengthInVehiclesSum="203" jamLengthInMetersSum="639.65" meanHaltingDuration="19.35" maxHaltingDuration="19.35" haltingDurationSum="19.35" meanIntervalHaltingDuration="10.15" maxIntervalHaltingDuration="10.15" intervalHaltingDurationSum="10.15" startedHalts="0.00" meanVehicleNumber="1.00" maxVehicleNumber="1" />
   <interval begin="208.35" end="211.35" id="e2_25" sampledSeconds="3.00" nVehEntered="0" nVehLeft="0" nVehSeen="1" meanSpeed="0.00" meanTimeLoss="3.00" meanOccupancy="9.00" maxOccupancy="9.00" meanMaxJamLengthInVehicles="1.00" meanMaxJamLengthInMeters="3.15" maxJamLengthInVehicles="1" maxJamLengthInMeters="3.15" jamLengthInVehiclesSum="60" jamLengthInMetersSum="189.06" meanHaltingDuration="22.35" maxHaltingDuration="22.35" haltingDurationSum="22.35" meanIntervalHaltingDuration="3.00" maxIntervalHaltingDuration="3.00" intervalHaltingDurationSum="3.00" startedHalts="0.00" meanVehicleNumber="1.00" maxVehicleNumber="1" />
   <interval begin="211.35" end="219.40" id="e2_25" sampledSeconds="1.64" nVehEntered="0" nVehLeft="1" nVehSeen="1" meanSpeed="1.92" meanTimeLoss="1.50" meanOccupancy="1.17" maxOccupancy="8.98" meanMaxJamLengthInVehicles="0.07" meanMaxJamLengthInMeters="0.20" maxJamLengthInVehicles="1" maxJamLengthInMeters="3.14" jamLengthInVehiclesSum="11" jamLengthInMetersSum="32.88" meanHaltingDuration="22.90" maxHaltingDuration="22.90" haltingDurationSum="22.90" meanIntervalHaltingDuration="0.55" maxIntervalHaltingDuration="0.55" intervalHaltingDurationSum="0.55" startedHalts="0.00" meanVehicleNumber="0.20" maxVehicleNumber="1" />
   <interval begin="219.40" end="222.40" id="e2_25" sampledSeconds="0.00" nVehEntered="0" nVehLeft="0" nVehSeen="0" meanSpeed="-1.00" meanTimeLoss="-1.00" meanOccupancy="0.00" maxOccupancy="0.00" meanMaxJamLengthInVehicles="0.00" meanMaxJamLengthInMeters="0.00" maxJamLengthInVehicles="0" maxJamLengthInMeters="0.00" jamLengthInVehiclesSum="0" jamLengthInMetersSum="0.00" meanHaltingDuration="0.00" maxHaltingDuration="0.00" haltingDurationSum="0.00" meanIntervalHaltingDuration="0.00" maxIntervalHaltingDuration="0.00" intervalHaltingDurationSum="0.00" startedHalts="0.00" meanVehicleNumber="0.00" maxVehicleNumber="0" />
   <interval begin="222.40" end="237.45" id="e2_25" sampledSeconds="0.00" nVehEntered="0" nVehLeft="0" nVehSeen="0" meanSpeed="-1.00" meanTimeLoss="-1.00" meanOccupancy="0.00" maxOccupancy="0.00" meanMaxJamLengthInVehicles="0.00" meanMaxJamLengthInMeters="0.00" maxJamLengthInVehicles="0" maxJamLengthInMeters="0.00" jamLengthInVehiclesSum="0" jamLengthInMetersSum="0.00" meanHaltingDuration="0.00" maxHaltingDuration="0.00" haltingDurationSum="0.00" meanIntervalHaltingDuration="0.00" maxIntervalHaltingDuration="0.00" intervalHaltingDurationSum="0.00" startedHalts="0.00" meanVehicleNumber="0.00" maxVehicleNumber="0" />
   <interval begin="237.45" end="240.45" id="e2_25" sampledSeconds="0.00" nVehEntered="0" nVehLeft="0" nVehSeen="0" meanSpeed="-1.00" meanTimeLoss="-1.00" meanOccupancy="0.00" maxOccupancy="0.00" meanMaxJamLengthInVehicles="0.00" meanMaxJamLengthInMeters="0.00" maxJamLengthInVehicles="0" maxJamLengthInMeters="0.00" jamLengthInVehiclesSum="0" jamLengthInMetersSum="0.00" meanHaltingDuration="0.00" maxHaltingDuration="0.00" haltingDurationSum="0.00" meanIntervalHaltingDuration="0.00" maxIntervalHaltingDuration="0.00" intervalHaltingDurationSum="0.00" startedHalts="0.00" meanVehicleNumber="0.00" maxVehicleNumber="0" />
   <interval begin="240.45" end="252.70" id="e2_25" sampledSeconds="0.00" nVehEntered="0" nVehLeft="0" nVehSeen="0" meanSpeed="-1.00" meanTimeLoss="-1.00" meanOccupancy="0.00" maxOccupancy="0.00" meanMaxJamLengthInVehicles="0.00" meanMaxJamLengthInMeters="0.00" maxJamLengthInVehicles="0" maxJamLengthInMeters="0.00" jamLengthInVehiclesSum="0" jamLengthInMetersSum="0.00" meanHaltingDuration="0.00" maxHaltingDuration="0.00" haltingDurationSum="0.00" meanIntervalHaltingDuration="0.00" maxIntervalHaltingDuration="0.00" intervalHaltingDurationSum="0.00" startedHalts="0.00" meanVehicleNumber="0.00" maxVehicleNumber="0" />
</detector>
